metamorphic_multifunction_search/__init__.py
metamorphic_multifunction_search/config/config.yaml
metamorphic_multifunction_search/config/constants.yaml
metamorphic_multifunction_search/main.py
metamorphic_multifunction_search/model.py
metamorphic_multifunction_search/operation/__init__.py
metamorphic_multifunction_search/operation/clustering/__init__.py
metamorphic_multifunction_search/operation/clustering/sequence_clustering.py
metamorphic_multifunction_search/operation/clustering/structural_subclustering.py
metamorphic_multifunction_search/operation/functional/__init__.py
metamorphic_multifunction_search/operation/functional/annotation_transfer/__init__.py
metamorphic_multifunction_search/operation/functional/annotation_transfer/methods/__init__.py
metamorphic_multifunction_search/operation/functional/annotation_transfer/methods/cosine_similarity.py
metamorphic_multifunction_search/operation/functional/annotation_transfer/sequence_go_annotation.py
metamorphic_multifunction_search/operation/functional/multifunctionality/__init__.py
metamorphic_multifunction_search/operation/functional/multifunctionality/go_multifunctionality_metrics.py
metamorphic_multifunction_search/operation/structural_alignment/__init__.py
metamorphic_multifunction_search/operation/structural_alignment/structural_alignment.py
metamorphic_multifunction_search/operation/structural_alignment/tasks/__init__.py
metamorphic_multifunction_search/operation/structural_alignment/tasks/combinatorial_extension.py
metamorphic_multifunction_search/operation/structural_alignment/tasks/fatcat.py
metamorphic_multifunction_search/operation/structural_alignment/tasks/universal.py
metamorphic_multifunction_search-4.2.0.dist-info/METADATA
metamorphic_multifunction_search-4.2.0.dist-info/WHEEL
metamorphic_multifunction_search-4.2.0.dist-info/RECORD
